aidev_ai_blueking-1.3.2.dist-info/METADATA
aidev_ai_blueking-1.3.2.dist-info/WHEEL
aidev_ai_blueking-1.3.2.dist-info/entry_points.txt
aidev_ai_blueking/__init__.py
aidev_ai_blueking/apps.py
aidev_ai_blueking/migrations/__init__.py
aidev_ai_blueking/settings.py
aidev_ai_blueking/static/css/Entry.b9cac39f.css
aidev_ai_blueking/static/css/Forbidden.3f6cb74f.css
aidev_ai_blueking/static/css/PageDemo.8cfa62cf.css
aidev_ai_blueking/static/css/Share.4109b3f3.css
aidev_ai_blueking/static/css/SideSliderDemo.dbaff690.css
aidev_ai_blueking/static/css/main.3ec853e8.css
aidev_ai_blueking/static/fonts/fontello.3f1fdcf0.ttf
aidev_ai_blueking/static/fonts/fontello.6c502925.eot
aidev_ai_blueking/static/fonts/fontello.6ec73abf.woff
aidev_ai_blueking/static/images/favicon.png
aidev_ai_blueking/static/js/143.dcc5fcb8.js
aidev_ai_blueking/static/js/145.0129e6f6.js
aidev_ai_blueking/static/js/146.5d71c7ab.js
aidev_ai_blueking/static/js/216.47c54ba5.js
aidev_ai_blueking/static/js/329.b8dd7001.js
aidev_ai_blueking/static/js/359.49b6cbab.js
aidev_ai_blueking/static/js/424.53977759.js
aidev_ai_blueking/static/js/437.771f6897.js
aidev_ai_blueking/static/js/456.f87b05b5.js
aidev_ai_blueking/static/js/475.343cfa49.js
aidev_ai_blueking/static/js/551.f60820ba.js
aidev_ai_blueking/static/js/574.ae094b8d.js
aidev_ai_blueking/static/js/604.1692cc72.js
aidev_ai_blueking/static/js/618.da89ae5c.js
aidev_ai_blueking/static/js/639.64f3508b.js
aidev_ai_blueking/static/js/69.a7a6d5d5.js
aidev_ai_blueking/static/js/73.beb0735e.js
aidev_ai_blueking/static/js/756.a9b525e8.js
aidev_ai_blueking/static/js/759.ec8a3b41.js
aidev_ai_blueking/static/js/821.3242499b.js
aidev_ai_blueking/static/js/840.5e4a5f41.js
aidev_ai_blueking/static/js/870.4514b8c0.js
aidev_ai_blueking/static/js/895.9357a710.js
aidev_ai_blueking/static/js/92.487cca2c.js
aidev_ai_blueking/static/js/Entry.83bed905.js
aidev_ai_blueking/static/js/Forbidden.dd43172f.js
aidev_ai_blueking/static/js/PageDemo.c35dbd76.js
aidev_ai_blueking/static/js/Share.e0bffa86.js
aidev_ai_blueking/static/js/SideSliderDemo.06b3d916.js
aidev_ai_blueking/static/js/chunk-bk-magic-vue.01f900de.js
aidev_ai_blueking-1.3.2.dist-info/RECORD
