Metadata-Version: 2.1
Name: aidev-ai-blueking
Version: 1.3.2
Summary: 小鲸静态资源包
Requires-Python: <4,>=3.11.9
Requires-Dist: aidev-agent<1.1,>=1.0.1
Requires-Dist: django<5.0,>=4.2.24
